graphein/__init__.py
graphein/cli.py
graphein/grn/__init__.py
graphein/grn/config.py
graphein/grn/edges.py
graphein/grn/graphs.py
graphein/grn/parse_regnetwork.py
graphein/grn/parse_trrust.py
graphein/grn/features/__init__.py
graphein/grn/features/node_features.py
graphein/ml/__init__.py
graphein/ml/clustering.py
graphein/ml/conversion.py
graphein/ml/diffusion.py
graphein/ml/utils.py
graphein/ml/visualisation.py
graphein/ml/datasets/__init__.py
graphein/ml/datasets/foldcomp_dataset.py
graphein/ml/datasets/pdb_data.py
graphein/ml/datasets/torch_geometric_dataset.py
graphein/ml/metrics/__init__.py
graphein/ml/metrics/gdt.py
graphein/ml/metrics/tm_score.py
graphein/molecule/__init__.py
graphein/molecule/atoms.py
graphein/molecule/chembl.py
graphein/molecule/config.py
graphein/molecule/graphs.py
graphein/molecule/utils.py
graphein/molecule/visualisation.py
graphein/molecule/zinc.py
graphein/molecule/edges/__init__.py
graphein/molecule/edges/atomic.py
graphein/molecule/edges/distance.py
graphein/molecule/features/__init__.py
graphein/molecule/features/edges/__init__.py
graphein/molecule/features/edges/bonds.py
graphein/molecule/features/graph/__init__.py
graphein/molecule/features/graph/molecule.py
graphein/molecule/features/nodes/__init__.py
graphein/molecule/features/nodes/atom_type.py
graphein/ppi/__init__.py
graphein/ppi/config.py
graphein/ppi/edges.py
graphein/ppi/graph_metadata.py
graphein/ppi/graphs.py
graphein/ppi/parse_biogrid.py
graphein/ppi/parse_stringdb.py
graphein/ppi/visualisation.py
graphein/ppi/features/__init__.py
graphein/ppi/features/node_features.py
graphein/protein/__init__.py
graphein/protein/analysis.py
graphein/protein/config.py
graphein/protein/folding_utils.py
graphein/protein/graphs.py
graphein/protein/meshes.py
graphein/protein/resi_atoms.py
graphein/protein/subgraphs.py
graphein/protein/utils.py
graphein/protein/visualisation.py
graphein/protein/edges/__init__.py
graphein/protein/edges/atomic.py
graphein/protein/edges/distance.py
graphein-1.7.8.dist-info/licenses/LICENSE
graphein-1.7.8.dist-info/METADATA
graphein-1.7.8.dist-info/WHEEL
graphein-1.7.8.dist-info/entry_points.txt
graphein-1.7.8.dist-info/top_level.txt
graphein-1.7.8.dist-info/RECORD
