Metadata-Version: 2.4
Name: graphein
Version: 1.7.8
Summary: Protein & Interactomic Graph Construction for Machine Learning
Home-page: https://github.com/a-r-j/graphein
Author: Arian Jamasb
Author-email: arian@jamasb.io
License: MIT
Project-URL: homepage, https://github.com/a-r-j/graphein
Project-URL: changelog, https://github.com/a-r-j/graphein/blob/master/CHANGELOG.md
Project-URL: issue, https://github.com/a-r-j/graphein/issues
Project-URL: documentation, https://graphein.ai/
Platform: any
Classifier: License :: OSI Approved :: MIT License
Classifier: Development Status :: 5 - Production/Stable
Classifier: Operating System :: Microsoft :: Windows
Classifier: Operating System :: POSIX
Classifier: Operating System :: Unix
Classifier: Operating System :: MacOS
Classifier: Programming Language :: Python :: 3.7
Classifier: Programming Language :: Python :: 3.8
Classifier: Programming Language :: Python :: 3.9
Classifier: Programming Language :: Python :: 3.10
Classifier: Programming Language :: Python :: 3.11
Classifier: Topic :: Scientific/Engineering
Requires-Python: >=3.7
License-File: LICENSE
Requires-Dist: pandas
Requires-Dist: biopandas>=0.5.1
Requires-Dist: biopython
Requires-Dist: bioservices>=1.10.0
Requires-Dist: cpdb-protein==0.2.0
Requires-Dist: cython
Requires-Dist: deepdiff
Requires-Dist: loguru
Requires-Dist: looseversion
Requires-Dist: matplotlib>=3.4.3
Requires-Dist: multipledispatch
Requires-Dist: networkx
Requires-Dist: numpy<2
Requires-Dist: pandas
Requires-Dist: plotly
Requires-Dist: pydantic
Requires-Dist: rich
Requires-Dist: rich-click
Requires-Dist: seaborn
Requires-Dist: pyyaml!=5.4.0,!=5.4.1,!=6.0.0
Requires-Dist: scikit-learn
Requires-Dist: scipy>=1.8
Requires-Dist: tqdm
Requires-Dist: wget
Requires-Dist: xarray
Requires-Dist: jaxtyping
Provides-Extra: dev
Requires-Dist: black; extra == "dev"
Requires-Dist: flake8; extra == "dev"
Requires-Dist: hypothesis; extra == "dev"
Requires-Dist: interrogate; extra == "dev"
Requires-Dist: isort; extra == "dev"
Requires-Dist: nbstripout; extra == "dev"
Requires-Dist: nbval; extra == "dev"
Requires-Dist: pandoc; extra == "dev"
Requires-Dist: pre-commit; extra == "dev"
Requires-Dist: pycodestyle; extra == "dev"
Requires-Dist: pydocstyle; extra == "dev"
Requires-Dist: pytest; extra == "dev"
Requires-Dist: pytest-cov; extra == "dev"
Requires-Dist: pytest-xdist; extra == "dev"
Provides-Extra: extras
Requires-Dist: biovec; extra == "extras"
Requires-Dist: propy3; extra == "extras"
Requires-Dist: pyaaisc; extra == "extras"
Requires-Dist: mpl_chord_diagram==0.3.2; extra == "extras"
Requires-Dist: rdkit; extra == "extras"
Requires-Dist: selfies; extra == "extras"
Requires-Dist: smilite; extra == "extras"
Requires-Dist: einops; extra == "extras"
Requires-Dist: foldcomp; extra == "extras"
Requires-Dist: nest_asyncio; extra == "extras"
Provides-Extra: all
Requires-Dist: pytest; extra == "all"
Requires-Dist: pre-commit; extra == "all"
Requires-Dist: pytest-cov; extra == "all"
Requires-Dist: nest_asyncio; extra == "all"
Requires-Dist: flake8; extra == "all"
Requires-Dist: pydocstyle; extra == "all"
Requires-Dist: smilite; extra == "all"
Requires-Dist: pandoc; extra == "all"
Requires-Dist: isort; extra == "all"
Requires-Dist: interrogate; extra == "all"
Requires-Dist: einops; extra == "all"
Requires-Dist: pyaaisc; extra == "all"
Requires-Dist: hypothesis; extra == "all"
Requires-Dist: pytest-xdist; extra == "all"
Requires-Dist: mpl_chord_diagram==0.3.2; extra == "all"
Requires-Dist: black; extra == "all"
Requires-Dist: foldcomp; extra == "all"
Requires-Dist: selfies; extra == "all"
Requires-Dist: nbval; extra == "all"
Requires-Dist: propy3; extra == "all"
Requires-Dist: nbstripout; extra == "all"
Requires-Dist: pycodestyle; extra == "all"
Requires-Dist: rdkit; extra == "all"
Requires-Dist: biovec; extra == "all"
Dynamic: author
Dynamic: author-email
Dynamic: classifier
Dynamic: description
Dynamic: description-content-type
Dynamic: home-page
Dynamic: license
Dynamic: license-file
Dynamic: platform
Dynamic: project-url
Dynamic: provides-extra
Dynamic: requires-dist
Dynamic: requires-python
Dynamic: summary
